jinheonsrandom/__init__.py
jinheonsrandom/main.py
jinheonsrandom-0.1.0.dist-info/LICENSE
jinheonsrandom-0.1.0.dist-info/METADATA
jinheonsrandom-0.1.0.dist-info/WHEEL
jinheonsrandom-0.1.0.dist-info/top_level.txt
jinheonsrandom-0.1.0.dist-info/RECORD
