Metadata-Version: 2.1
Name: jinheonsrandom
Version: 0.1.0
Summary: Use Jinheon's random!
Home-page: https://github.com/Jueuunn7/jujak
Author: Jueuunn7
Author-email: wndmsrla1234@gmail.com
Classifier: Programming Language :: Python :: 3
Classifier: License :: OSI Approved :: MIT License
License-File: LICENSE
